{
    "recipe_name": "Bông So Đũa Chiên Giòn",
    "serving": "4 người",
    "times": "30 Phút",
    "difficulty": "Dễ",
    "normal_ingredients": [
        "Bông so đũa: 100g",
        "Cá thác lác: 200g",
        "Giò sống: 50g",
        "Hành tỏi băm Hành lá: 2 nhánh",
        "Nước mắm, tiêu, dầu ăn, tương ớt",
        "Ớt sừng băm"
    ],
    "spices": [
        "Aji-Quick® Bột Chiên Giòn",
        "Xốt Mayonnaise Aji-mayo® Vị Nguyên Bản"
    ],
    "process": [
        "Cá thác lác quết nhuyễn với 1/2m nước mắm.",
        "Trộn hỗn hợp gồm: giò sống, cá thác lác, hành tỏi băm, hành lá cắt nhuyễn, ớt băm và 1/2m tiêu. Bông so đũa ngắt bỏ nhụy. Nhồi hỗn hợp vào bông so đũa.",
        "Pha 1 gói Aji-Quick® Bột Chiên Giòn Hải Sản với nước theo tỷ lệ ghi trên bao bì. Để 10 phút."
    ],
    "cook": [
        "Đun nóng dầu ăn, lần lượt nhúng bông so đũa vào hỗn hợp bột, đem chiên trong chảo ngập dầu đến khi chín vàng. Vớt ra để ráo."
    ],
    "usage": [
        "1)."
    ],
    "tips": [
        "Nhồi nhân vào bông so đũa nhẹ tay để không làm gãy cánh.",
        "Ngắt nhụy bông so đũa nhằm giảm vị đắng và chát."
    ]
}