{
    "recipe_name": "Dồi Trường Xào Bông Hẹ",
    "serving": "4 người",
    "times": "10 Phút",
    "difficulty": "Dễ",
    "normal_ingredients": [
        "Dồi trường: 300g",
        "Bông hẹ: 200g",
        "Hành tây: 50g",
        "Ớt chuông đỏ, vàng: 50g",
        "Hành tỏi băm: 2M",
        "Gừng: 1M",
        "ĂN KÈM: Cơm nóng",
        "Gia vị: Đường, tiêu, dầu ăn, rượu trắng, dầu hào"
    ],
    "spices": [
        "Hạt nêm Aji-ngon® Heo",
        "Nước tương \"Phú Sĩ\"",
        "Bột ngọt AJI-NO-MOTO®"
    ],
    "process": [
        "Dồi trường rửa sạch, ngâm nước có pha chút rượu và gừng đập dập rồi rửa sạch lại cho vô tô nước đá 30 phút, cắt khúc 2cm.",
        "Bông hẹ rửa sạch, bỏ phần già, cắt khúc 3 – 4cm.",
        "Hành tây cắt sợi 5cm. Ớt chuông bỏ hạt, cắt miếng vừa ăn.",
        "Gừng cắt sợi nhuyễn."
    ],
    "cook": [
        "Pha xốt: 1/2m đường, 1.5m hạt nêm Heo, 1/2m bột ngọt, 1/2m tiêu, 1M dầu hào, ít rượu trắng và 1M nước.",
        "Phi thơm 1M hành tỏi băm, 1M gừng, cho dồi trường vào xào lửa lớn, đảo thật nhanh tay, cho nửa lượng xốt đã pha vào, xào dồi trường chín tới thêm hành tây, trút ra dĩa.",
        "Đun nóng dầu, phi thơm 1M hành tỏi băm, cho bông hẹ và ớt chuông vào xào, cho phần xốt còn lại vào xào, bông hẹ sắp chín cho dồi trường vào trộn nhanh tay, tắt lửa."
    ],
    "usage": [],
    "tips": []
}