{
    "recipe_name": "Má Heo Nướng Táo",
    "serving": "4 người",
    "times": "60 Phút",
    "difficulty": "Dễ",
    "normal_ingredients": [
        "Thịt má heo: 500g",
        "Hành tím băm: 1M",
        "Tỏi băm: 1/2M",
        "Nước táo hộp: 200ml",
        "Tương cà Heinz: 2M",
        "Tương ớt: 1M",
        "Mè trắng rang: 1M",
        "Bột ớt Hàn Quốc: 1M",
        "Sữa đặc có đường: 1M",
        "ĂN KÈM: Dưa cải, rau thơm, muối ớt tắc",
        "Gia vị: Dầu ăn, muối, dầu hào, bột ngũ vị hương, baking soda, rượu trắng"
    ],
    "spices": [
        "Bột ngọt AJI-NO-MOTO®",
        "Hạt nêm Aji-ngon® Heo"
    ],
    "process": [],
    "cook": [],
    "usage": [],
    "tips": []
}