{
    "recipe_name": "Bacon Cuộn Hành Tây Phô Mai",
    "serving": "4 người",
    "times": "10 Phút",
    "difficulty": "Dễ",
    "normal_ingredients": [
        "Bacon: 300g",
        "Hành tây nguyên củ to dài: 300g",
        "Ham lát: 4 lát",
        "Phô mai Mozzarella: 100g",
        "Cà chua bi vàng + đỏ: 150g",
        "Salad carol: 50g",
        "Ôliu đen: 20 trái",
        "Lá Thyme tươi: 1 nhánh",
        "Tăm xiên: 10 cây",
        "RAU NÊM: ớt bột"
    ],
    "spices": [
        "Xốt Mayonnaise Aji-mayo® Vị Ngọt Dịu"
    ],
    "process": [
        "Hành tây cắt khoanh tròn dày 10cm sau đó tách ra từng khoanh, bacon cắt làm đôi theo chiều dọc, ham lát cắt thành những lát nhỏ 10cm.",
        "Phô mai Mozzarella cắt thành những lát mỏng và có chiều dài 10cm, ngang 1cm."
    ],
    "cook": [
        "Cho khoanh hành tây lớn lên thớt sau đó lần lượt cho ham lát và phô mai Mozzarella.",
        "Tiếp theo là chọn khoanh hành tây nhỏ hơn cho vào trong và rắc thêm một ít lá Thyme tươi lên trên dùng bacon cuộn chặt xung quanh vòng hành tây và dùng tăm cố định bacon và làm lần lượt đến khi hết nguyên liệu.",
        "Chiên bacon: Cho dầu vào chảo đợi dầu nóng sau đó cho bacon vào chiên ngập dầu với lửa lớn cho vàng giòn và vớt ra giấy thấm dầu, tiếp theo cho cà chua vào chiên sơ."
    ],
    "usage": [],
    "tips": [
        "Bacon cuộn chặt tay giúp khi chiên phô mai không bị chảy ra ngoài.",
        "Sử dụng Xốt Mayonnaise Aji-mayo® Ngọt Dịu giúp món ăn được cân bằng vị hơn.",
        "Cho lá Thyme tươi vào trong củ hành tây giúp tạo ra hương vị thơm đặc trưng cho món ăn."
    ]
}