{
    "recipe_name": "Canh Gà Lá Quế",
    "serving": "4 người",
    "times": "30 Phút",
    "difficulty": "Dễ",
    "normal_ingredients": [
        "Gà ta 1/2 con",
        "Rau quế 100g",
        "Hành tây 1 củ nhỏ",
        "Hành lá 2 cây",
        "Ớt hiểm xanh 10 trái",
        "Ớt hiểm đỏ 5 trái",
        "Dừa tươi 1 trái",
        "Tỏi phi, ngò gai, sả băm , tỏi băm",
        "ĂN KÈM: Bún tươi và nước mắm ớt.",
        "Gia vị: Dầu ăn, muối, đường, nước mắm"
    ],
    "spices": [
        "\"AJINOMOTO\" Giấm gạo lên men",
        "Hạt nêm Aji-ngon® Gà",
        "Bột ngọt AJI-NO-MOTO®"
    ],
    "process": [
        "Gà chặt miếng vừa ăn, ướp với 1/2M Hạt nêm Aji-ngon® (Gà), để 15 phút cho thấm gia vị.",
        "Hành tây cắt múi cau. Hành lá cắt khúc. Ớt hiểm xanh, đỏ đập dập. Rau quế cắt khúc."
    ],
    "cook": [],
    "usage": [],
    "tips": [
        "Xào gà kỹ để thịt gà thấm vị, săn và ngon hơn.",
        "Nêm nước mắm vào sau cùng tạo vị đậm đà cho món ăn."
    ]
}